{
  "System Name": "Lakeland City Services (Project 25) System",
  "Location": "Lakeland, FL",
  "County": "Polk",
  "System Type": "Project 25 Phase II",
  "System Voice": "APCO-25 Common Air Interface Exclusive",
  "Last Updated": "June 29, 2018, 8:51 am (Imported Talkgroups (16 Imported, 0 Updated))",
  "System ID List": [
    {
      "System ID": "573",
      "WACN": "BEE00"
    }
  ],
  "System Frequencies": [
    {
      "RFSS": "1 (1)",
      "Site": "001 (1)",
      "Name": "Simulcast",
      "Freqs": [
        "854.7125",
        "855.2375",
        "855.7375",
        "856.4125a",
        "857.1125",
        "858.4125a",
        "858.7625a",
        "859.1125",
        "859.7625c"
      ]
    }
  ],
  "System Talkgroups": [
    {
      "DEC ": "81 ",
      "HEX ": "051 ",
      "Mode  ": "T",
      "Alpha Tag": "LFR 81",
      "Description": "Fire-Rescue 81 ",
      "Tag  ": "Fire-Tac "
    },
    {
      "DEC ": "83 ",
      "HEX ": "053 ",
      "Mode  ": "T",
      "Alpha Tag": "LFR 83",
      "Description": "Fire-Rescue 83 ",
      "Tag  ": "Fire-Tac "
    },
    {
      "DEC ": "85 ",
      "HEX ": "055 ",
      "Mode  ": "T",
      "Alpha Tag": "LFR 85",
      "Description": "Fire-Rescue 85 ",
      "Tag  ": "Fire-Tac "
    },
    {
      "DEC ": "1001 ",
      "HEX ": "3e9 ",
      "Mode  ": "T",
      "Alpha Tag": "LFR-1",
      "Description": "Fire-Rescue Toneouts 1 ",
      "Tag  ": "Fire Dispatch "
    },
    {
      "DEC ": "1002 ",
      "HEX ": "3ea ",
      "Mode  ": "T",
      "Alpha Tag": "LFR-2",
      "Description": "Fire-Rescue Toneouts 2 ",
      "Tag  ": "Fire Dispatch "
    },
    {
      "DEC ": "1003 ",
      "HEX ": "3eb ",
      "Mode  ": "T",
      "Alpha Tag": "LFR-3",
      "Description": "Fire-Rescue Toneouts 3 ",
      "Tag  ": "Fire Dispatch "
    },
    {
      "DEC ": "1004 ",
      "HEX ": "3ec ",
      "Mode  ": "T",
      "Alpha Tag": "LFR-4",
      "Description": "Fire-Rescue Toneouts 4 ",
      "Tag  ": "Fire Dispatch "
    },
    {
      "DEC ": "1005 ",
      "HEX ": "3ed ",
      "Mode  ": "T",
      "Alpha Tag": "LFR-5",
      "Description": "Fire-Rescue Toneouts 5 ",
      "Tag  ": "Fire Dispatch "
    },
    {
      "DEC ": "1006 ",
      "HEX ": "3ee ",
      "Mode  ": "T",
      "Alpha Tag": "LFR-6",
      "Description": "Fire-Rescue Toneouts 6 ",
      "Tag  ": "Fire Dispatch "
    },
    {
      "DEC ": "1007 ",
      "HEX ": "3ef ",
      "Mode  ": "T",
      "Alpha Tag": "LFR-7",
      "Description": "Fire-Rescue Toneouts 7 ",
      "Tag  ": "Fire Dispatch "
    }
  ],
  "undefined": [
    {
      "DEC ": "113 ",
      "HEX ": "071 ",
      "Mode  ": "T",
      "Alpha Tag": "Electric 113",
      "Description": "Electric Operations 113 ",
      "Tag  ": "Public Works "
    },
    {
      "DEC ": "115 ",
      "HEX ": "073 ",
      "Mode  ": "T",
      "Alpha Tag": "Electric 115",
      "Description": "Electric Operations 115 ",
      "Tag  ": "Public Works "
    },
    {
      "DEC ": "117 ",
      "HEX ": "075 ",
      "Mode  ": "T",
      "Alpha Tag": "Electric 117",
      "Description": "Electric Operations 117 ",
      "Tag  ": "Public Works "
    },
    {
      "DEC ": "125 ",
      "HEX ": "07d ",
      "Mode  ": "T",
      "Alpha Tag": "Lakeland Ctr",
      "Description": "Lakeland Center Security ",
      "Tag  ": "Security "
    },
    {
      "DEC ": "147 ",
      "HEX ": "093 ",
      "Mode  ": "T",
      "Alpha Tag": "Sanitation 147",
      "Description": "Solid Waste - Sanitation 147 ",
      "Tag  ": "Public Works "
    },
    {
      "DEC ": "149 ",
      "HEX ": "095 ",
      "Mode  ": "T",
      "Alpha Tag": "Sanitation 149",
      "Description": "Solid Waste - Sanitation 149 ",
      "Tag  ": "Public Works "
    }
  ]
}