{
  "System Name": "Supreme Radio Communications (East Peoria)",
  "Location": "East Peoria, IL",
  "County": "3 counties",
  "System Type": "Motorola Type IIi Hybrid",
  "System Voice": "Analog",
  "Last Updated": "May 23, 2018, 2:09 am (Added a new news entry)",
  "System ID List": [
    {
      "System ID": "AA03",
      "Connect Tone": "128.57"
    }
  ],
  "System Fleetmap": [
    {
      "Type": "Mot",
      "B0": "2",
      "B1": "",
      "B2": "2",
      "B3": "2",
      "B4": "2",
      "B5": "2",
      "B6": "2",
      "B7": ""
    },
    {
      "Type": "TT",
      "B0": "S0",
      "B1": "",
      "B2": "S0",
      "B3": "S0",
      "B4": "S0",
      "B5": "S0",
      "B6": "S0",
      "B7": ""
    }
  ],
  "System Frequencies": [
    {
      "Site": "001 (1)",
      "Name": "East Peoria ",
      "County": "Tazewell",
      "Freqs": [
        "855.0875c",
        "855.2875",
        "855.5875",
        "855.7625",
        "856.6875",
        "857.6875",
        "857.7875",
        "858.6875",
        "859.6875",
        "856.1125c",
        "857.1125c",
        "858.1125",
        "859.1125",
        "860.1125",
        "856.5125c",
        "857.5125",
        "858.5125",
        "859.5125",
        "860.5125",
        "854.1375",
        "854.7375",
        "854.4125"
      ]
    }
  ],
  "System Talkgroups": [
    {
      "Subfleet ": "0  ",
      "DEC ": "52800 ",
      "HEX ": "ce4 ",
      "Mode  ": "A",
      "Alpha Tag": "AMT Peoria",
      "Description": "EMS: Peoria County ",
      "Tag  ": "Deprecated "
    },
    {
      "Subfleet ": "0  ",
      "DEC ": "52816 ",
      "HEX ": "ce5 ",
      "Mode  ": "A",
      "Alpha Tag": "AMT Tazewell",
      "Description": "EMS: Tazewell County / Link to TAZCOMM ",
      "Tag  ": "Deprecated "
    },
    {
      "Subfleet ": "0  ",
      "DEC ": "57328 ",
      "HEX ": "dff ",
      "Mode  ": "A",
      "Alpha Tag": "AMT Peoria2",
      "Description": "EMS: Peoria 2 ",
      "Tag  ": "EMS-Tac "
    }
  ],
  "undefined": [
    {
      "Subfleet ": "0  ",
      "DEC ": "272 ",
      "HEX ": "011 ",
      "Mode  ": "A",
      "Alpha Tag": "taxi 272",
      "Description": "taxi company ",
      "Tag  ": "Transportation "
    },
    {
      "Subfleet ": "0  ",
      "DEC ": "528 ",
      "HEX ": "021 ",
      "Mode  ": "A",
      "Alpha Tag": "trucking528",
      "Description": "trucking company ",
      "Tag  ": "Business "
    },
    {
      "Subfleet ": "0  ",
      "DEC ": "720 ",
      "HEX ": "02d ",
      "Mode  ": "A",
      "Alpha Tag": "trucking720",
      "Description": "trucking company ",
      "Tag  ": "Business "
    },
    {
      "Subfleet ": "0  ",
      "DEC ": "2064 ",
      "HEX ": "081 ",
      "Mode  ": "A",
      "Alpha Tag": "ag 2064",
      "Description": "agricultural plant ops ",
      "Tag  ": "Business "
    },
    {
      "Subfleet ": "0  ",
      "DEC ": "4176 ",
      "HEX ": "105 ",
      "Mode  ": "A",
      "Alpha Tag": "Peoria City",
      "Description": "Peoria City - private use (possibly city manager) ",
      "Tag  ": "Public Works "
    },
    {
      "Subfleet ": "0  ",
      "DEC ": "25664 ",
      "HEX ": "644 ",
      "Mode  ": "A",
      "Alpha Tag": "trash 25664",
      "Description": "garbage company ",
      "Tag  ": "Business "
    },
    {
      "Subfleet ": "0  ",
      "DEC ": "27712 ",
      "HEX ": "6c4 ",
      "Mode  ": "A",
      "Alpha Tag": "snow 27712",
      "Description": "snow plows ",
      "Tag  ": "Business "
    },
    {
      "Subfleet ": "0  ",
      "DEC ": "35025 ",
      "HEX ": "88d ",
      "Mode  ": "A",
      "Alpha Tag": "trash 35025",
      "Description": "garbage company ",
      "Tag  ": "Business "
    },
    {
      "Subfleet ": "0  ",
      "DEC ": "35040 ",
      "HEX ": "88e ",
      "Mode  ": "A",
      "Alpha Tag": "trash 35040",
      "Description": "garbage company ",
      "Tag  ": "Business "
    },
    {
      "Subfleet ": "0  ",
      "DEC ": "35104 ",
      "HEX ": "892 ",
      "Mode  ": "A",
      "Alpha Tag": "trash 35104",
      "Description": "garbage company ",
      "Tag  ": "Business "
    },
    {
      "Subfleet ": "0  ",
      "DEC ": "35120 ",
      "HEX ": "893 ",
      "Mode  ": "A",
      "Alpha Tag": "trash 35120",
      "Description": "garbage company ",
      "Tag  ": "Business "
    },
    {
      "Subfleet ": "0  ",
      "DEC ": "35168 ",
      "HEX ": "896 ",
      "Mode  ": "A",
      "Alpha Tag": "trash 35168",
      "Description": "garbage company ",
      "Tag  ": "Business "
    },
    {
      "Subfleet ": "0  ",
      "DEC ": "35184 ",
      "HEX ": "897 ",
      "Mode  ": "A",
      "Alpha Tag": "trash 35814",
      "Description": "garbage company ",
      "Tag  ": "Business "
    },
    {
      "Subfleet ": "0  ",
      "DEC ": "49424 ",
      "HEX ": "c11 ",
      "Mode  ": "A",
      "Alpha Tag": "Am Peo/Pek 1",
      "Description": "Ameren: Peoria/Pekin ",
      "Tag  ": "Utilities "
    },
    {
      "Subfleet ": "0  ",
      "DEC ": "50064 ",
      "HEX ": "c39 ",
      "Mode  ": "A",
      "Alpha Tag": "Am Peo/Pek 2",
      "Description": "Ameren: Peoria/Pekin ",
      "Tag  ": "Utilities "
    },
    {
      "Subfleet ": "0  ",
      "DEC ": "50096 ",
      "HEX ": "c3b ",
      "Mode  ": "A",
      "Alpha Tag": "Am Peo/Pek 3",
      "Description": "Ameren: Peoria/Pekin ",
      "Tag  ": "Utilities "
    }
  ]
}