{
  "System Name": "Indianapolis Airport Authority (TRBO)",
  "Location": "Indianapolis, IN",
  "County": "Marion",
  "System Type": "DMR Motorola Capacity Plus Single Site (TRBO)",
  "System Voice": "DMR",
  "Last Updated": "July 15, 2017, 6:38 pm (Updated General Trunked System Information)",
  "System Frequencies": [
    {
      "Site": "001 (1)",
      "Name": [
        "Airport",
        "01 453.275 ",
        "02 453.325 ",
        "03 453.475 ",
        "04 453.575 ",
        "05 453.975 ",
        "06 460.0625 ",
        "07 460.575 "
      ]
    }
  ]
}