{
  "System Name": "Lee County Public Safety (P25)",
  "Location": "Fort Myers, FL",
  "County": "Lee",
  "System Type": "Project 25 Phase I",
  "System Voice": "APCO-25 Common Air Interface Exclusive",
  "Last Updated": "January 27, 2019, 4:43 pm (Added Talkgroup 615 EMS Air Operations(Lee County Fire/EMS))",
  "System ID List": [
    {
      "System ID": "361",
      "WACN": "BEE00"
    }
  ],
  "System Frequencies": [
    {
      "RFSS": "1 (1)",
      "Site": "001 (1)",
      "Name": "Simulcast",
      "Freqs": [
        "855.6625a",
        "855.9625c",
        "856.2375",
        "857.2375",
        "858.2375",
        "859.2375",
        " ",
        " "
      ]
    },
    {
      "RFSS": "1 (1)",
      "Site": "002 (2)",
      "Name": "Sanibel",
      "Freqs": [
        "851.400a",
        "851.625",
        "851.875a",
        "852.125c",
        "855.7125a",
        " ",
        " ",
        " "
      ]
    },
    {
      "RFSS": "1 (1)",
      "Site": "003 (3)",
      "Name": "Boca Grande",
      "Freqs": [
        "851.050",
        "854.5875",
        "854.9625",
        "856.2125c",
        "856.2125",
        "856.7125",
        "857.4625",
        "858.4625",
        "859.0875"
      ]
    }
  ],
  "System Talkgroups": [
    {
      "DEC ": "2861 ",
      "HEX ": "b2d ",
      "Mode  ": "D",
      "Alpha Tag": "LCSO Disp1 N",
      "Description": "Dispatch 1 Mode 1 (North) ",
      "Tag  ": "Law Dispatch "
    },
    {
      "DEC ": "2863 ",
      "HEX ": "b2f ",
      "Mode  ": "D",
      "Alpha Tag": "LCSO Disp2 E",
      "Description": "Dispatch 2 Mode 2 (East) ",
      "Tag  ": "Law Dispatch "
    },
    {
      "DEC ": "2865 ",
      "HEX ": "b31 ",
      "Mode  ": "D",
      "Alpha Tag": "LCSO Disp5 C",
      "Description": "Dispatch 5 (Central) ",
      "Tag  ": "Law Dispatch "
    },
    {
      "DEC ": "2867 ",
      "HEX ": "b33 ",
      "Mode  ": "DE",
      "Alpha Tag": "LCSO Disp4 S",
      "Description": "Dispatch 4 (South) ",
      "Tag  ": "Law Dispatch "
    },
    {
      "DEC ": "2869 ",
      "HEX ": "b35 ",
      "Mode  ": "D",
      "Alpha Tag": "NCIC Disp",
      "Description": "NCIC Dispatch ",
      "Tag  ": "Law Dispatch "
    },
    {
      "DEC ": "2873 ",
      "HEX ": "b39 ",
      "Mode  ": "D",
      "Alpha Tag": "LCSO Traffic",
      "Description": "Traffic ",
      "Tag  ": "Law Tac "
    },
    {
      "DEC ": "2885 ",
      "HEX ": "b45 ",
      "Mode  ": "DE",
      "Alpha Tag": "LCSO Tac 1 N",
      "Description": "Tactical 1 (North) ",
      "Tag  ": "Law Tac "
    },
    {
      "DEC ": "46192 ",
      "HEX ": "b470 ",
      "Mode  ": "DE",
      "Alpha Tag": "LCSO Tac 2 E",
      "Description": "Tactical 2 (East) ",
      "Tag  ": "Law Tac "
    }
  ],
  "undefined": [
    {
      "DEC ": "1199 ",
      "HEX ": "4af ",
      "Mode  ": "D",
      "Alpha Tag": "CCFD 1199",
      "Description": "Fire ",
      "Tag  ": "Fire-Tac "
    },
    {
      "DEC ": "1191 ",
      "HEX ": "4a7 ",
      "Mode  ": "D",
      "Alpha Tag": "CCFD M/M",
      "Description": "Fire (M/M) ",
      "Tag  ": "Fire-Tac "
    },
    {
      "DEC ": "1181 ",
      "HEX ": "49d ",
      "Mode  ": "D",
      "Alpha Tag": "CCFD Disp",
      "Description": "Fire Dispatch ",
      "Tag  ": "Fire Dispatch "
    },
    {
      "DEC ": "1193 ",
      "HEX ": "4a9 ",
      "Mode  ": "D",
      "Alpha Tag": "CCFD Prevent",
      "Description": "Fire Prevention ",
      "Tag  ": "Fire-Talk "
    },
    {
      "DEC ": "1206 ",
      "HEX ": "4b6 ",
      "Mode  ": "D",
      "Alpha Tag": "CCFD Tac1206",
      "Description": "Fire Tactical ",
      "Tag  ": "Fire-Tac "
    },
    {
      "DEC ": "1209 ",
      "HEX ": "4b9 ",
      "Mode  ": "D",
      "Alpha Tag": "CCFD Tac 1",
      "Description": "Fire Tactical 1 ",
      "Tag  ": "Fire-Tac "
    },
    {
      "DEC ": "1183 ",
      "HEX ": "49f ",
      "Mode  ": "D",
      "Alpha Tag": "CCFD Tac 2",
      "Description": "Fire Tactical 2 ",
      "Tag  ": "Fire-Tac "
    },
    {
      "DEC ": "1185 ",
      "HEX ": "4a1 ",
      "Mode  ": "D",
      "Alpha Tag": "CCFD Tac 3",
      "Description": "Fire Tactical 3 ",
      "Tag  ": "Fire-Tac "
    },
    {
      "DEC ": "1187 ",
      "HEX ": "4a3 ",
      "Mode  ": "D",
      "Alpha Tag": "CCFD Tac 4",
      "Description": "Fire Tactical 4 ",
      "Tag  ": "Fire-Tac "
    },
    {
      "DEC ": "1211 ",
      "HEX ": "4bb ",
      "Mode  ": "D",
      "Alpha Tag": "CCFD Tac 5",
      "Description": "Fire Tactical 5 ",
      "Tag  ": "Fire-Tac "
    },
    {
      "DEC ": "1213 ",
      "HEX ": "4bd ",
      "Mode  ": "D",
      "Alpha Tag": "CCFD Tac 6",
      "Description": "Fire Tactical 6 ",
      "Tag  ": "Fire-Tac "
    },
    {
      "DEC ": "1215 ",
      "HEX ": "4bf ",
      "Mode  ": "D",
      "Alpha Tag": "CCFD Tac 7",
      "Description": "Fire Tactical 7 ",
      "Tag  ": "Fire-Tac "
    },
    {
      "DEC ": "1141 ",
      "HEX ": "475 ",
      "Mode  ": "DE",
      "Alpha Tag": "CCPD 1141",
      "Description": "Police ",
      "Tag  ": "Law Talk "
    },
    {
      "DEC ": "1133 ",
      "HEX ": "46d ",
      "Mode  ": "DE",
      "Alpha Tag": "CCPD 2",
      "Description": "Police 2 ",
      "Tag  ": "Law Talk "
    },
    {
      "DEC ": "1137 ",
      "HEX ": "471 ",
      "Mode  ": "DE",
      "Alpha Tag": "CCPD 3 C-C",
      "Description": "Police 3 Car-Car ",
      "Tag  ": "Law Talk "
    },
    {
      "DEC ": "1139 ",
      "HEX ": "473 ",
      "Mode  ": "DE",
      "Alpha Tag": "CCPD CID",
      "Description": "Police CID ",
      "Tag  ": "Law Tac "
    },
    {
      "DEC ": "1131 ",
      "HEX ": "46b ",
      "Mode  ": "DE",
      "Alpha Tag": "CCPD Disp1 S",
      "Description": "Police Dispatch 1 (South) ",
      "Tag  ": "Law Dispatch "
    },
    {
      "DEC ": "1155 ",
      "HEX ": "483 ",
      "Mode  ": "DE",
      "Alpha Tag": "CCPD Disp2 N",
      "Description": "Police Dispatch 2 (North) ",
      "Tag  ": "Law Dispatch "
    },
    {
      "DEC ": "1149 ",
      "HEX ": "47d ",
      "Mode  ": "DE",
      "Alpha Tag": "CCPD Events1",
      "Description": "Police Events 1 ",
      "Tag  ": "Law Tac "
    },
    {
      "DEC ": "1151 ",
      "HEX ": "47f ",
      "Mode  ": "DE",
      "Alpha Tag": "CCPD Events2",
      "Description": "Police Events 2 ",
      "Tag  ": "Law Tac "
    },
    {
      "DEC ": "1143 ",
      "HEX ": "477 ",
      "Mode  ": "DE",
      "Alpha Tag": "CCPD Foxtrot",
      "Description": "Police Foxtrot ",
      "Tag  ": "Law Tac "
    },
    {
      "DEC ": "1135 ",
      "HEX ": "46f ",
      "Mode  ": "DE",
      "Alpha Tag": "CCPD Record1",
      "Description": "Police Records for Dispatch 1 (Teletype) ",
      "Tag  ": "Law Tac "
    },
    {
      "DEC ": "1145 ",
      "HEX ": "479 ",
      "Mode  ": "DE",
      "Alpha Tag": "CCPD Record2",
      "Description": "Police Records for Dispatch 2 (Teletype) ",
      "Tag  ": "Law Tac "
    }
  ]
}