{
  "System Name": "MedComm",
  "Location": "Various, ME",
  "County": "5 counties",
  "System Type": "DMR Motorola Capacity Plus Multi Site (TRBO)",
  "System Voice": "DMR",
  "Last Updated": "December 27, 2016, 10:51 am (Changed Site # 000 (Falmouth) to 000 (Falmouth))",
  "System Frequencies": [
    {
      "Site": "000 (0)",
      "Name": "Falmouth",
      "County": [
        "Cumberland",
        "01 153.0125 "
      ]
    },
    {
      "Site": "001 (1)",
      "Name": "Camden",
      "County": [
        "Knox",
        "01 152.975 "
      ]
    },
    {
      "Site": "001 (1)",
      "Name": "Orrington",
      "County": [
        "Penobscot",
        "01 151.715 "
      ]
    },
    {
      "Site": "002 (2)",
      "Name": "Dresden",
      "County": [
        "Lincoln",
        "01 151.850 "
      ]
    },
    {
      "Site": "005 (5)",
      "Name": "Sanford",
      "County": [
        "York",
        "01 151.925 "
      ]
    }
  ],
  "System Talkgroups": [
    {
      "DEC ": "20 ",
      "Mode  ": "T",
      "Alpha Tag": "Medical Tran",
      "Description": "Medical Transport ",
      "Tag  ": "EMS-Talk "
    },
    {
      "DEC ": "22 ",
      "Mode  ": "T",
      "Alpha Tag": "Medical Tran",
      "Description": "Medical Transport ",
      "Tag  ": "EMS-Talk "
    }
  ]
}