{
  "System Name": "Miami-Dade County",
  "Location": "Miami, FL",
  "County": "Miami-Dade",
  "System Type": "Project 25 Phase I",
  "System Voice": "APCO-25 Common Air Interface Exclusive",
  "Last Updated": "January 11, 2019, 1:32 pm ((14) Talkgroups Updated (Miami-Dade Police Department))",
  "System ID List": [
    {
      "System ID": "065",
      "WACN": "92A5E"
    }
  ],
  "System Frequencies": [
    {
      "RFSS": "101 (65)",
      "Site": "001 (1)",
      "Name": "Miami - TCC",
      "Freqs": [
        "851.1125a",
        "851.1375a",
        "851.3625a",
        "851.3875a",
        "851.6125a",
        "851.6375a",
        "851.8625a",
        "851.8875a",
        "852.1375a",
        "852.2875a",
        "852.3875a",
        "852.5375a",
        "852.6625c",
        "852.9125a",
        "853.1125a",
        "853.2625a",
        "853.3625a",
        "853.5125a",
        "853.6125a",
        "853.8625a"
      ]
    },
    {
      "RFSS": "102 (66)",
      "Site": "001 (1)",
      "Name": "Site 102",
      "Freqs": [
        "851.0375a",
        "851.0625a",
        "851.2875a",
        "851.3125a",
        "851.5625a",
        "851.7625a",
        "851.8125a",
        "852.0625a",
        "852.1125a",
        "852.3625a",
        "852.4125a",
        "852.5625a",
        "852.7875a",
        "852.8125a",
        "853.1375c",
        "853.1625a",
        "853.3875a",
        "853.4125a",
        "853.6375a",
        "853.8875a"
      ]
    },
    {
      "RFSS": "103 (67)",
      "Site": "001 (1)",
      "Name": "Site 103",
      "Freqs": [
        "851.7375c",
        "852.2375",
        "852.6875",
        "853.2375",
        "853.7375",
        " ",
        " ",
        " "
      ]
    },
    {
      "RFSS": "104 (68)",
      "Site": "001 (1)",
      "Name": "Miccosukee - 40 Mile Bend",
      "Freqs": [
        "769.09375",
        "769.61875c",
        "770.61875",
        "771.74375",
        "772.76875",
        " ",
        " ",
        " "
      ]
    },
    {
      "RFSS": "108 (6C)",
      "Site": "001 (1)",
      "Name": "CAB (SPCC)",
      "Freqs": [
        "769.08125a",
        "769.35625c",
        "769.60625",
        "769.85625",
        "770.10625a",
        "770.35625",
        "770.60625",
        "770.85625",
        "771.10625",
        "771.35625a",
        "771.73125a",
        "771.98125",
        "772.25625",
        "772.50625",
        "772.75625"
      ]
    },
    {
      "RFSS": "109 (6D)",
      "Site": "001 (1)",
      "Name": "Sunny Isles Beach",
      "Freqs": [
        "855.0125a",
        "855.8875a",
        "858.4625c",
        " ",
        " ",
        " ",
        " ",
        " "
      ]
    },
    {
      "RFSS": "136 (88)",
      "Site": "001 (1)",
      "Name": "Key Biscayne ",
      "Freqs": [
        "770.11875",
        "770.36875c",
        "771.11875",
        "771.36875",
        "772.26875",
        " ",
        " ",
        " "
      ]
    }
  ],
  "System Talkgroups": [
    {
      "DEC ": "10000 ",
      "HEX ": "2710 ",
      "Mode  ": "D",
      "Alpha Tag": "MDC-1",
      "Description": "Miami-Dade County 1 ",
      "Tag  ": "Other "
    },
    {
      "DEC ": "10001 ",
      "HEX ": "2711 ",
      "Mode  ": "D",
      "Alpha Tag": "MDC-2",
      "Description": "Miami-Dade County 2 ",
      "Tag  ": "Other "
    },
    {
      "DEC ": "10002 ",
      "HEX ": "2712 ",
      "Mode  ": "D",
      "Alpha Tag": "MDC-3",
      "Description": "Miami-Dade County 3 ",
      "Tag  ": "Other "
    },
    {
      "DEC ": "10003 ",
      "HEX ": "2713 ",
      "Mode  ": "D",
      "Alpha Tag": "MDC-4",
      "Description": "Miami-Dade County 4 ",
      "Tag  ": "Other "
    },
    {
      "DEC ": "10004 ",
      "HEX ": "2714 ",
      "Mode  ": "D",
      "Alpha Tag": "MDC-5",
      "Description": "Miami-Dade County 5 ",
      "Tag  ": "Other "
    }
  ],
  "undefined": [
    {
      "DEC ": "10800 ",
      "HEX ": "2a30 ",
      "Mode  ": "D",
      "Alpha Tag": "Micco PD",
      "Description": "Police ",
      "Tag  ": "Law Tac "
    }
  ]
}