{
  "System Name": "Electronic Applications",
  "Location": "Burlington, IA",
  "County": "Des Moines",
  "System Type": "LTR Standard",
  "System Voice": "Analog",
  "Last Updated": "August 25, 2016, 2:35 am (Updated Talkgroups (3 Updated))",
  "System Frequencies": [
    {
      "Site": "001 (1)",
      "Name": [
        "Confirmed LCN",
        "01 463.2375 ",
        "02 461.8875 "
      ]
    },
    {
      "Site": "002 (2)",
      "Name": [
        "Unconfirmed LCN",
        "01 461.3875 ",
        " "
      ]
    }
  ],
  "System Talkgroups": [
    {
      "DEC ": "0-01-010 ",
      "Mode  ": "A",
      "Alpha Tag": "cabs 1010",
      "Description": "taxi cab company ",
      "Tag  ": "Transportation "
    },
    {
      "DEC ": "0-02-010 ",
      "Mode  ": "A",
      "Alpha Tag": "cabs 2010",
      "Description": "taxi cab company ",
      "Tag  ": "Transportation "
    },
    {
      "DEC ": "0-02-020 ",
      "Mode  ": "A",
      "Alpha Tag": "cabs 2020",
      "Description": "taxi cab company ",
      "Tag  ": "Transportation "
    }
  ]
}