{
  "System Name": "Davis-Monthan Air Force Base",
  "Location": "Tucson, AZ",
  "County": "Pima",
  "System Type": "Project 25 Phase I",
  "System Voice": "APCO-25 Common Air Interface Exclusive",
  "Last Updated": "November 19, 2018, 1:04 am (Updated General Trunked System Information)",
  "System ID List": [
    {
      "System ID": "3F6",
      "WACN": "BEE00"
    }
  ],
  "System Frequencies": [
    {
      "RFSS": "1 (1)",
      "Site": "002 (2)",
      "Name": "Site 2",
      "Freqs": [
        "407.8125",
        "407.8875",
        "408.050",
        "408.0875",
        "408.125",
        "408.150",
        "408.5625",
        "409.025",
        "409.275c",
        "409.450a",
        "409.5625a",
        "410.5625a"
      ]
    }
  ],
  "System Talkgroups": [
    {
      "DEC ": "256 ",
      "HEX ": "100 ",
      "Mode  ": "D",
      "Alpha Tag": "AMARC-1",
      "Description": "AMARC Net-1 ",
      "Tag  ": "Military "
    },
    {
      "DEC ": "257 ",
      "HEX ": "101 ",
      "Mode  ": "D",
      "Alpha Tag": "AMARC-2",
      "Description": "AMARC Net-2 ",
      "Tag  ": "Military "
    },
    {
      "DEC ": "258 ",
      "HEX ": "102 ",
      "Mode  ": "D",
      "Alpha Tag": "AMARC-3",
      "Description": "AMARC Net-3 ",
      "Tag  ": "Military "
    },
    {
      "DEC ": "259 ",
      "HEX ": "103 ",
      "Mode  ": "D",
      "Alpha Tag": "AMARC-4",
      "Description": "AMARC Net-4 ",
      "Tag  ": "Military "
    },
    {
      "DEC ": "260 ",
      "HEX ": "104 ",
      "Mode  ": "D",
      "Alpha Tag": "AMARC-5",
      "Description": "AMARC Net-5 ",
      "Tag  ": "Military "
    },
    {
      "DEC ": "261 ",
      "HEX ": "105 ",
      "Mode  ": "D",
      "Alpha Tag": "AMARC-All",
      "Description": "AMARC-Control All-Call ",
      "Tag  ": "Military "
    }
  ],
  "undefined": [
    {
      "DEC ": "10 ",
      "HEX ": "00a ",
      "Mode  ": "D",
      "Alpha Tag": "Announcement",
      "Description": "Announcement Group ",
      "Tag  ": "Military "
    }
  ]
}